README.md
setup.py
owlet_api/__init__.py
owlet_api/cli.py
owlet_api/owlet.py
owlet_api/owletapi.py
owlet_api/owletexceptions.py
owlet_api/owletproperty.py
owlet_api.egg-info/PKG-INFO
owlet_api.egg-info/SOURCES.txt
owlet_api.egg-info/dependency_links.txt
owlet_api.egg-info/entry_points.txt
owlet_api.egg-info/requires.txt
owlet_api.egg-info/top_level.txt